{
	"@type":"Hierarchy",
	"Name":"De Montfort",
	"Elements":
	[
		{
			"Name":"DM01",
			"Type":"Numeric"
		},
		{
			"Name":"DM02",
			"Type":"Numeric"
		},
		{
			"Name":"DM08",
			"Type":"Numeric"
		},
		{
			"Name":"DM09",
			"Type":"Numeric"
		},
		{
			"Name":"DM11",
			"Type":"Numeric"
		},
		{
			"Name":"DM12",
			"Type":"Numeric"
		},
		{
			"Name":"DM13",
			"Type":"Numeric"
		},
		{
			"Name":"DM14",
			"Type":"Numeric"
		},
		{
			"Name":"All De Montfort",
			"Type":"Numeric"
		}
	],
	"Subsets@Code.links":[]
}