{
	"@type":"Hierarchy",
	"Name":"MA_Dept",
	"Elements":
	[
		{
			"Name":"ALL DEPTS",
			"Type":"Consolidated"
		},
		{
			"Name":"GRPALC",
			"Type":"Numeric"
		},
		{
			"Name":"GRPBDZ",
			"Type":"Numeric"
		},
		{
			"Name":"GRPFBS",
			"Type":"Numeric"
		},
		{
			"Name":"GRPFMG",
			"Type":"Numeric"
		},
		{
			"Name":"GRPFTR",
			"Type":"Numeric"
		},
		{
			"Name":"GRPHRZ",
			"Type":"Numeric"
		},
		{
			"Name":"GRPITZ",
			"Type":"Numeric"
		},
		{
			"Name":"GRPLEG",
			"Type":"Numeric"
		},
		{
			"Name":"GRPOTH",
			"Type":"Numeric"
		},
		{
			"Name":"GRPPRJ",
			"Type":"Numeric"
		},
		{
			"Name":"GSCADM",
			"Type":"Numeric"
		},
		{
			"Name":"GSCBFZ",
			"Type":"Numeric"
		},
		{
			"Name":"GSCCSM",
			"Type":"Numeric"
		},
		{
			"Name":"GSCCSS",
			"Type":"Numeric"
		},
		{
			"Name":"GSCFAP",
			"Type":"Numeric"
		},
		{
			"Name":"GSCFAR",
			"Type":"Numeric"
		},
		{
			"Name":"GSCFBL",
			"Type":"Numeric"
		},
		{
			"Name":"GSCFBS",
			"Type":"Numeric"
		},
		{
			"Name":"GSCFGL",
			"Type":"Numeric"
		},
		{
			"Name":"GSCFMG",
			"Type":"Numeric"
		},
		{
			"Name":"GSCFTR",
			"Type":"Numeric"
		},
		{
			"Name":"GSCITZ",
			"Type":"Numeric"
		},
		{
			"Name":"LOCBDM",
			"Type":"Numeric"
		},
		{
			"Name":"LOCBDZ",
			"Type":"Numeric"
		},
		{
			"Name":"LOCCSM",
			"Type":"Numeric"
		},
		{
			"Name":"LOCCSS",
			"Type":"Numeric"
		},
		{
			"Name":"LOCHRZ",
			"Type":"Numeric"
		},
		{
			"Name":"LOCITZ",
			"Type":"Numeric"
		},
		{
			"Name":"LOCOTH",
			"Type":"Numeric"
		},
		{
			"Name":"LOCPRJ",
			"Type":"Numeric"
		},
		{
			"Name":"OTHERZ",
			"Type":"Numeric"
		},
		{
			"Name":"REGBDZ",
			"Type":"Numeric"
		},
		{
			"Name":"REGFNC",
			"Type":"Numeric"
		},
		{
			"Name":"Client Services Local",
			"Type":"Consolidated"
		},
		{
			"Name":"Finance Local",
			"Type":"Consolidated"
		},
		{
			"Name":"BD Local",
			"Type":"Consolidated"
		},
		{
			"Name":"Other Local",
			"Type":"Consolidated"
		},
		{
			"Name":"Other Gross Wages & Salaries",
			"Type":"Consolidated"
		},
		{
			"Name":"GSC Allocation",
			"Type":"Consolidated"
		},
		{
			"Name":"Client Services GSC",
			"Type":"Consolidated"
		},
		{
			"Name":"Finance GSC",
			"Type":"Consolidated"
		},
		{
			"Name":"BD GSC",
			"Type":"Consolidated"
		},
		{
			"Name":"Other GSC",
			"Type":"Consolidated"
		},
		{
			"Name":"Non GSC Allocation",
			"Type":"Consolidated"
		},
		{
			"Name":"Local CS",
			"Type":"Numeric"
		},
		{
			"Name":"Local Finance",
			"Type":"Consolidated"
		},
		{
			"Name":"Regional Admin",
			"Type":"Consolidated"
		},
		{
			"Name":"Other allocated",
			"Type":"Numeric"
		},
		{
			"Name":"Local Salaries",
			"Type":"Consolidated"
		},
		{
			"Name":"Unallocated Dept",
			"Type":"Consolidated"
		},
		{
			"Name":"GRPALM",
			"Type":"Numeric"
		},
		{
			"Name":"GRPITD",
			"Type":"Numeric"
		},
		{
			"Name":"ZZZ",
			"Type":"Numeric"
		},
		{
			"Name":"GRPFTM",
			"Type":"Numeric"
		},
		{
			"Name":"Group",
			"Type":"Consolidated"
		},
		{
			"Name":"IT Group",
			"Type":"Numeric"
		},
		{
			"Name":"Admin Group",
			"Type":"Consolidated"
		},
		{
			"Name":"Projects Group",
			"Type":"Numeric"
		},
		{
			"Name":"Other Group",
			"Type":"Consolidated"
		},
		{
			"Name":"GRPFDV",
			"Type":"Numeric"
		},
		{
			"Name":"Finance Group",
			"Type":"Consolidated"
		},
		{
			"Name":"ROLLUP 2",
			"Type":"Consolidated"
		},
		{
			"Name":"Balance Sheet",
			"Type":"Consolidated"
		},
		{
			"Name":"Rollup 1",
			"Type":"Consolidated"
		},
		{
			"Name":"2019",
			"Type":"Numeric"
		},
		{
			"Name":"2020",
			"Type":"Numeric"
		},
		{
			"Name":"2021",
			"Type":"Numeric"
		},
		{
			"Name":"2022",
			"Type":"Numeric"
		},
		{
			"Name":"2023",
			"Type":"Numeric"
		},
		{
			"Name":"2024",
			"Type":"Numeric"
		},
		{
			"Name":"GRPFIT",
			"Type":"Numeric"
		},
		{
			"Name":"GRPMKT",
			"Type":"Numeric"
		},
		{
			"Name":"GRPADM",
			"Type":"Numeric"
		},
		{
			"Name":"GSC",
			"Type":"Consolidated"
		},
		{
			"Name":"GSC 1",
			"Type":"Consolidated"
		},
		{
			"Name":"Local",
			"Type":"Consolidated"
		},
		{
			"Name":"LOCFAP",
			"Type":"Numeric"
		},
		{
			"Name":"LOCFAR",
			"Type":"Numeric"
		},
		{
			"Name":"LOCFBL",
			"Type":"Numeric"
		},
		{
			"Name":"LOCFGL",
			"Type":"Numeric"
		},
		{
			"Name":"LOCFMG",
			"Type":"Numeric"
		},
		{
			"Name":"Unassigned",
			"Type":"Consolidated"
		},
		{
			"Name":"Regional",
			"Type":"Consolidated"
		},
		{
			"Name":"Rollup 3",
			"Type":"Consolidated"
		},
		{
			"Name":"Admin",
			"Type":"Consolidated"
		},
		{
			"Name":"Group Admin",
			"Type":"Consolidated"
		},
		{
			"Name":"Group - Finance",
			"Type":"Consolidated"
		},
		{
			"Name":"GSC - Admin",
			"Type":"Consolidated"
		},
		{
			"Name":"Local - Other",
			"Type":"Consolidated"
		},
		{
			"Name":"Regional - Other",
			"Type":"Consolidated"
		},
		{
			"Name":"HR",
			"Type":"Consolidated"
		},
		{
			"Name":"Group - HR",
			"Type":"Consolidated"
		},
		{
			"Name":"BD",
			"Type":"Consolidated"
		},
		{
			"Name":"Group - BD",
			"Type":"Consolidated"
		},
		{
			"Name":"GSC - BD",
			"Type":"Consolidated"
		},
		{
			"Name":"Local - BD",
			"Type":"Consolidated"
		},
		{
			"Name":"Group- Legal",
			"Type":"Numeric"
		},
		{
			"Name":"2018",
			"Type":"Numeric"
		},
		{
			"Name":"Client Services",
			"Type":"Consolidated"
		},
		{
			"Name":"GSC - Client Services",
			"Type":"Consolidated"
		},
		{
			"Name":"Local - Client Services",
			"Type":"Consolidated"
		},
		{
			"Name":"Finance",
			"Type":"Consolidated"
		},
		{
			"Name":"Local - Finance",
			"Type":"Consolidated"
		},
		{
			"Name":"GSC - Finance",
			"Type":"Consolidated"
		},
		{
			"Name":"IT",
			"Type":"Consolidated"
		},
		{
			"Name":"Group IT Finance",
			"Type":"Consolidated"
		},
		{
			"Name":"Group - Finance IT",
			"Type":"Consolidated"
		},
		{
			"Name":"Group - Finance IT DEV",
			"Type":"Consolidated"
		},
		{
			"Name":"Group - Finance TFM",
			"Type":"Consolidated"
		},
		{
			"Name":"Projects",
			"Type":"Consolidated"
		},
		{
			"Name":"Group - Projects",
			"Type":"Consolidated"
		},
		{
			"Name":"PRDACC",
			"Type":"Numeric"
		},
		{
			"Name":"PRDAIR",
			"Type":"Numeric"
		},
		{
			"Name":"PRDCAR",
			"Type":"Numeric"
		},
		{
			"Name":"PRDOTH",
			"Type":"Numeric"
		},
		{
			"Name":"PRDRAI",
			"Type":"Numeric"
		},
		{
			"Name":"STRCOR",
			"Type":"Numeric"
		},
		{
			"Name":"STRESM",
			"Type":"Numeric"
		},
		{
			"Name":"STROTH",
			"Type":"Numeric"
		},
		{
			"Name":"PRDCON",
			"Type":"Numeric"
		},
		{
			"Name":"PRDPKG",
			"Type":"Numeric"
		},
		{
			"Name":"STRGOV",
			"Type":"Numeric"
		},
		{
			"Name":"PRDBUS",
			"Type":"Numeric"
		}
	],
	"Edges":
	[
		{
			"ParentName":"ALL DEPTS",
			"ComponentName":"Local Salaries",
			"Weight":1
		},
		{
			"ParentName":"ALL DEPTS",
			"ComponentName":"GSC Allocation",
			"Weight":1
		},
		{
			"ParentName":"ALL DEPTS",
			"ComponentName":"Non GSC Allocation",
			"Weight":1
		},
		{
			"ParentName":"ALL DEPTS",
			"ComponentName":"Group",
			"Weight":1
		},
		{
			"ParentName":"ALL DEPTS",
			"ComponentName":"Unallocated Dept",
			"Weight":1
		},
		{
			"ParentName":"Client Services Local",
			"ComponentName":"LOCCSM",
			"Weight":1
		},
		{
			"ParentName":"Client Services Local",
			"ComponentName":"LOCCSS",
			"Weight":1
		},
		{
			"ParentName":"Finance Local",
			"ComponentName":"LOCFGL",
			"Weight":1
		},
		{
			"ParentName":"BD Local",
			"ComponentName":"LOCBDM",
			"Weight":1
		},
		{
			"ParentName":"BD Local",
			"ComponentName":"LOCBDZ",
			"Weight":1
		},
		{
			"ParentName":"Other Local",
			"ComponentName":"LOCITZ",
			"Weight":1
		},
		{
			"ParentName":"Other Local",
			"ComponentName":"LOCOTH",
			"Weight":1
		},
		{
			"ParentName":"Other Local",
			"ComponentName":"LOCPRJ",
			"Weight":1
		},
		{
			"ParentName":"Other Local",
			"ComponentName":"LOCHRZ",
			"Weight":1
		},
		{
			"ParentName":"GSC Allocation",
			"ComponentName":"Client Services GSC",
			"Weight":1
		},
		{
			"ParentName":"GSC Allocation",
			"ComponentName":"Finance GSC",
			"Weight":1
		},
		{
			"ParentName":"GSC Allocation",
			"ComponentName":"BD GSC",
			"Weight":1
		},
		{
			"ParentName":"GSC Allocation",
			"ComponentName":"Other GSC",
			"Weight":1
		},
		{
			"ParentName":"Client Services GSC",
			"ComponentName":"GSCCSM",
			"Weight":1
		},
		{
			"ParentName":"Client Services GSC",
			"ComponentName":"GSCCSS",
			"Weight":1
		},
		{
			"ParentName":"Client Services GSC",
			"ComponentName":"GSCADM",
			"Weight":1
		},
		{
			"ParentName":"Finance GSC",
			"ComponentName":"GSCFAP",
			"Weight":1
		},
		{
			"ParentName":"Finance GSC",
			"ComponentName":"GSCFAR",
			"Weight":1
		},
		{
			"ParentName":"Finance GSC",
			"ComponentName":"GSCFBL",
			"Weight":1
		},
		{
			"ParentName":"Finance GSC",
			"ComponentName":"GSCFBS",
			"Weight":1
		},
		{
			"ParentName":"Finance GSC",
			"ComponentName":"GSCFGL",
			"Weight":1
		},
		{
			"ParentName":"Finance GSC",
			"ComponentName":"GSCFMG",
			"Weight":1
		},
		{
			"ParentName":"Finance GSC",
			"ComponentName":"GSCFTR",
			"Weight":1
		},
		{
			"ParentName":"BD GSC",
			"ComponentName":"GSCBFZ",
			"Weight":1
		},
		{
			"ParentName":"Other GSC",
			"ComponentName":"GSCITZ",
			"Weight":1
		},
		{
			"ParentName":"Non GSC Allocation",
			"ComponentName":"Local CS",
			"Weight":1
		},
		{
			"ParentName":"Non GSC Allocation",
			"ComponentName":"Local Finance",
			"Weight":1
		},
		{
			"ParentName":"Non GSC Allocation",
			"ComponentName":"Regional Admin",
			"Weight":1
		},
		{
			"ParentName":"Non GSC Allocation",
			"ComponentName":"Other allocated",
			"Weight":1
		},
		{
			"ParentName":"Local Finance",
			"ComponentName":"REGFNC",
			"Weight":1
		},
		{
			"ParentName":"Regional Admin",
			"ComponentName":"REGBDZ",
			"Weight":1
		},
		{
			"ParentName":"Local Salaries",
			"ComponentName":"Client Services Local",
			"Weight":1
		},
		{
			"ParentName":"Local Salaries",
			"ComponentName":"Finance Local",
			"Weight":1
		},
		{
			"ParentName":"Local Salaries",
			"ComponentName":"BD Local",
			"Weight":1
		},
		{
			"ParentName":"Local Salaries",
			"ComponentName":"Other Local",
			"Weight":1
		},
		{
			"ParentName":"Local Salaries",
			"ComponentName":"Other Gross Wages & Salaries",
			"Weight":1
		},
		{
			"ParentName":"Unallocated Dept",
			"ComponentName":"OTHERZ",
			"Weight":1
		},
		{
			"ParentName":"Group",
			"ComponentName":"GRPADM",
			"Weight":1
		},
		{
			"ParentName":"Group",
			"ComponentName":"GRPPRJ",
			"Weight":1
		},
		{
			"ParentName":"Group",
			"ComponentName":"GRPOTH",
			"Weight":1
		},
		{
			"ParentName":"Group",
			"ComponentName":"GRPMKT",
			"Weight":1
		},
		{
			"ParentName":"Group",
			"ComponentName":"GRPLEG",
			"Weight":1
		},
		{
			"ParentName":"Group",
			"ComponentName":"GRPITZ",
			"Weight":1
		},
		{
			"ParentName":"Group",
			"ComponentName":"GRPITD",
			"Weight":1
		},
		{
			"ParentName":"Group",
			"ComponentName":"GRPHRZ",
			"Weight":1
		},
		{
			"ParentName":"Group",
			"ComponentName":"GRPFTR",
			"Weight":1
		},
		{
			"ParentName":"Group",
			"ComponentName":"GRPFTM",
			"Weight":1
		},
		{
			"ParentName":"Group",
			"ComponentName":"GRPFMG",
			"Weight":1
		},
		{
			"ParentName":"Group",
			"ComponentName":"GRPFIT",
			"Weight":1
		},
		{
			"ParentName":"Group",
			"ComponentName":"GRPFBS",
			"Weight":1
		},
		{
			"ParentName":"Group",
			"ComponentName":"GRPBDZ",
			"Weight":1
		},
		{
			"ParentName":"Group",
			"ComponentName":"GRPALM",
			"Weight":1
		},
		{
			"ParentName":"Group",
			"ComponentName":"GRPALC",
			"Weight":1
		},
		{
			"ParentName":"Group",
			"ComponentName":"Finance Group",
			"Weight":1
		},
		{
			"ParentName":"Group",
			"ComponentName":"IT Group",
			"Weight":1
		},
		{
			"ParentName":"Group",
			"ComponentName":"Admin Group",
			"Weight":1
		},
		{
			"ParentName":"Group",
			"ComponentName":"Projects Group",
			"Weight":1
		},
		{
			"ParentName":"Group",
			"ComponentName":"Other Group",
			"Weight":1
		},
		{
			"ParentName":"Other Group",
			"ComponentName":"ZZZ",
			"Weight":1
		},
		{
			"ParentName":"Finance Group",
			"ComponentName":"GRPFDV",
			"Weight":1
		},
		{
			"ParentName":"Finance Group",
			"ComponentName":"GRPFBS",
			"Weight":1
		},
		{
			"ParentName":"Finance Group",
			"ComponentName":"GRPFTR",
			"Weight":1
		},
		{
			"ParentName":"ROLLUP 2",
			"ComponentName":"Balance Sheet",
			"Weight":1
		},
		{
			"ParentName":"Balance Sheet",
			"ComponentName":"2018",
			"Weight":1
		},
		{
			"ParentName":"Balance Sheet",
			"ComponentName":"2019",
			"Weight":1
		},
		{
			"ParentName":"Balance Sheet",
			"ComponentName":"2020",
			"Weight":1
		},
		{
			"ParentName":"Balance Sheet",
			"ComponentName":"2021",
			"Weight":1
		},
		{
			"ParentName":"Balance Sheet",
			"ComponentName":"2022",
			"Weight":1
		},
		{
			"ParentName":"Balance Sheet",
			"ComponentName":"2023",
			"Weight":1
		},
		{
			"ParentName":"Balance Sheet",
			"ComponentName":"2024",
			"Weight":1
		},
		{
			"ParentName":"Rollup 1",
			"ComponentName":"Regional",
			"Weight":1
		},
		{
			"ParentName":"Rollup 1",
			"ComponentName":"Unassigned",
			"Weight":1
		},
		{
			"ParentName":"Rollup 1",
			"ComponentName":"Local",
			"Weight":1
		},
		{
			"ParentName":"Rollup 1",
			"ComponentName":"GSC 1",
			"Weight":1
		},
		{
			"ParentName":"Rollup 1",
			"ComponentName":"Group",
			"Weight":1
		},
		{
			"ParentName":"Rollup 1",
			"ComponentName":"Balance Sheet",
			"Weight":1
		},
		{
			"ParentName":"GSC",
			"ComponentName":"GSCADM",
			"Weight":1
		},
		{
			"ParentName":"GSC",
			"ComponentName":"GSCBFZ",
			"Weight":1
		},
		{
			"ParentName":"GSC",
			"ComponentName":"GSCCSM",
			"Weight":1
		},
		{
			"ParentName":"GSC",
			"ComponentName":"GSCCSS",
			"Weight":1
		},
		{
			"ParentName":"GSC",
			"ComponentName":"GSCFAP",
			"Weight":1
		},
		{
			"ParentName":"GSC",
			"ComponentName":"GSCFAR",
			"Weight":1
		},
		{
			"ParentName":"GSC",
			"ComponentName":"GSCFBL",
			"Weight":1
		},
		{
			"ParentName":"GSC",
			"ComponentName":"GSCFBS",
			"Weight":1
		},
		{
			"ParentName":"GSC",
			"ComponentName":"GSCFGL",
			"Weight":1
		},
		{
			"ParentName":"GSC",
			"ComponentName":"GSCFMG",
			"Weight":1
		},
		{
			"ParentName":"GSC",
			"ComponentName":"GSCFTR",
			"Weight":1
		},
		{
			"ParentName":"GSC",
			"ComponentName":"GSCITZ",
			"Weight":1
		},
		{
			"ParentName":"GSC 1",
			"ComponentName":"GSCADM",
			"Weight":1
		},
		{
			"ParentName":"GSC 1",
			"ComponentName":"GSCBFZ",
			"Weight":1
		},
		{
			"ParentName":"GSC 1",
			"ComponentName":"GSCCSM",
			"Weight":1
		},
		{
			"ParentName":"GSC 1",
			"ComponentName":"GSCCSS",
			"Weight":1
		},
		{
			"ParentName":"GSC 1",
			"ComponentName":"GSCFAP",
			"Weight":1
		},
		{
			"ParentName":"GSC 1",
			"ComponentName":"GSCFAR",
			"Weight":1
		},
		{
			"ParentName":"GSC 1",
			"ComponentName":"GSCFBL",
			"Weight":1
		},
		{
			"ParentName":"GSC 1",
			"ComponentName":"GSCFBS",
			"Weight":1
		},
		{
			"ParentName":"GSC 1",
			"ComponentName":"GSCFGL",
			"Weight":1
		},
		{
			"ParentName":"GSC 1",
			"ComponentName":"GSCFMG",
			"Weight":1
		},
		{
			"ParentName":"GSC 1",
			"ComponentName":"GSCFTR",
			"Weight":1
		},
		{
			"ParentName":"GSC 1",
			"ComponentName":"GSCITZ",
			"Weight":1
		},
		{
			"ParentName":"Local",
			"ComponentName":"LOCPRJ",
			"Weight":1
		},
		{
			"ParentName":"Local",
			"ComponentName":"LOCOTH",
			"Weight":1
		},
		{
			"ParentName":"Local",
			"ComponentName":"LOCITZ",
			"Weight":1
		},
		{
			"ParentName":"Local",
			"ComponentName":"LOCHRZ",
			"Weight":1
		},
		{
			"ParentName":"Local",
			"ComponentName":"LOCFMG",
			"Weight":1
		},
		{
			"ParentName":"Local",
			"ComponentName":"LOCFGL",
			"Weight":1
		},
		{
			"ParentName":"Local",
			"ComponentName":"LOCFBL",
			"Weight":1
		},
		{
			"ParentName":"Local",
			"ComponentName":"LOCFAR",
			"Weight":1
		},
		{
			"ParentName":"Local",
			"ComponentName":"LOCFAP",
			"Weight":1
		},
		{
			"ParentName":"Local",
			"ComponentName":"LOCCSS",
			"Weight":1
		},
		{
			"ParentName":"Local",
			"ComponentName":"LOCCSM",
			"Weight":1
		},
		{
			"ParentName":"Local",
			"ComponentName":"LOCBDZ",
			"Weight":1
		},
		{
			"ParentName":"Local",
			"ComponentName":"LOCBDM",
			"Weight":1
		},
		{
			"ParentName":"Unassigned",
			"ComponentName":"OTHERZ",
			"Weight":1
		},
		{
			"ParentName":"Regional",
			"ComponentName":"REGFNC",
			"Weight":1
		},
		{
			"ParentName":"Regional",
			"ComponentName":"REGBDZ",
			"Weight":1
		},
		{
			"ParentName":"Rollup 3",
			"ComponentName":"Unassigned",
			"Weight":1
		},
		{
			"ParentName":"Rollup 3",
			"ComponentName":"Projects",
			"Weight":1
		},
		{
			"ParentName":"Rollup 3",
			"ComponentName":"IT",
			"Weight":1
		},
		{
			"ParentName":"Rollup 3",
			"ComponentName":"Finance",
			"Weight":1
		},
		{
			"ParentName":"Rollup 3",
			"ComponentName":"Client Services",
			"Weight":1
		},
		{
			"ParentName":"Rollup 3",
			"ComponentName":"Balance Sheet",
			"Weight":1
		},
		{
			"ParentName":"Rollup 3",
			"ComponentName":"Admin",
			"Weight":1
		},
		{
			"ParentName":"Admin",
			"ComponentName":"Group- Legal",
			"Weight":1
		},
		{
			"ParentName":"Admin",
			"ComponentName":"BD",
			"Weight":1
		},
		{
			"ParentName":"Admin",
			"ComponentName":"HR",
			"Weight":1
		},
		{
			"ParentName":"Admin",
			"ComponentName":"Regional - Other",
			"Weight":1
		},
		{
			"ParentName":"Admin",
			"ComponentName":"Local - Other",
			"Weight":1
		},
		{
			"ParentName":"Admin",
			"ComponentName":"GSC - Admin",
			"Weight":1
		},
		{
			"ParentName":"Admin",
			"ComponentName":"Group - Finance",
			"Weight":1
		},
		{
			"ParentName":"Admin",
			"ComponentName":"Group Admin",
			"Weight":1
		},
		{
			"ParentName":"Group Admin",
			"ComponentName":"GRPADM",
			"Weight":1
		},
		{
			"ParentName":"Group - Finance",
			"ComponentName":"GRPFMG",
			"Weight":1
		},
		{
			"ParentName":"GSC - Admin",
			"ComponentName":"GSCADM",
			"Weight":1
		},
		{
			"ParentName":"Local - Other",
			"ComponentName":"LOCPRJ",
			"Weight":1
		},
		{
			"ParentName":"Regional - Other",
			"ComponentName":"REGFNC",
			"Weight":1
		},
		{
			"ParentName":"HR",
			"ComponentName":"Local - Other",
			"Weight":1
		},
		{
			"ParentName":"HR",
			"ComponentName":"Group - HR",
			"Weight":1
		},
		{
			"ParentName":"Group - HR",
			"ComponentName":"GRPHRZ",
			"Weight":1
		},
		{
			"ParentName":"BD",
			"ComponentName":"Regional - Other",
			"Weight":1
		},
		{
			"ParentName":"BD",
			"ComponentName":"Local - BD",
			"Weight":1
		},
		{
			"ParentName":"BD",
			"ComponentName":"GSC - BD",
			"Weight":1
		},
		{
			"ParentName":"BD",
			"ComponentName":"Group - BD",
			"Weight":1
		},
		{
			"ParentName":"Group - BD",
			"ComponentName":"GRPBDZ",
			"Weight":1
		},
		{
			"ParentName":"GSC - BD",
			"ComponentName":"GSCBFZ",
			"Weight":1
		},
		{
			"ParentName":"Local - BD",
			"ComponentName":"LOCBDZ",
			"Weight":1
		},
		{
			"ParentName":"Local - BD",
			"ComponentName":"LOCBDM",
			"Weight":1
		},
		{
			"ParentName":"Client Services",
			"ComponentName":"Local - Client Services",
			"Weight":1
		},
		{
			"ParentName":"Client Services",
			"ComponentName":"GSC - Client Services",
			"Weight":1
		},
		{
			"ParentName":"GSC - Client Services",
			"ComponentName":"GSCCSS",
			"Weight":1
		},
		{
			"ParentName":"GSC - Client Services",
			"ComponentName":"GSCCSM",
			"Weight":1
		},
		{
			"ParentName":"Local - Client Services",
			"ComponentName":"LOCCSS",
			"Weight":1
		},
		{
			"ParentName":"Local - Client Services",
			"ComponentName":"LOCCSM",
			"Weight":1
		},
		{
			"ParentName":"Finance",
			"ComponentName":"GSC - Finance",
			"Weight":1
		},
		{
			"ParentName":"Finance",
			"ComponentName":"Regional - Other",
			"Weight":1
		},
		{
			"ParentName":"Finance",
			"ComponentName":"Local - Finance",
			"Weight":1
		},
		{
			"ParentName":"Local - Finance",
			"ComponentName":"LOCFMG",
			"Weight":1
		},
		{
			"ParentName":"Local - Finance",
			"ComponentName":"LOCFGL",
			"Weight":1
		},
		{
			"ParentName":"Local - Finance",
			"ComponentName":"LOCFBL",
			"Weight":1
		},
		{
			"ParentName":"Local - Finance",
			"ComponentName":"LOCFAR",
			"Weight":1
		},
		{
			"ParentName":"Local - Finance",
			"ComponentName":"LOCFAP",
			"Weight":1
		},
		{
			"ParentName":"GSC - Finance",
			"ComponentName":"GSCFTR",
			"Weight":1
		},
		{
			"ParentName":"GSC - Finance",
			"ComponentName":"GSCFMG",
			"Weight":1
		},
		{
			"ParentName":"GSC - Finance",
			"ComponentName":"GSCFGL",
			"Weight":1
		},
		{
			"ParentName":"GSC - Finance",
			"ComponentName":"GSCFBS",
			"Weight":1
		},
		{
			"ParentName":"GSC - Finance",
			"ComponentName":"GSCFBL",
			"Weight":1
		},
		{
			"ParentName":"GSC - Finance",
			"ComponentName":"GSCFAR",
			"Weight":1
		},
		{
			"ParentName":"GSC - Finance",
			"ComponentName":"GSCFAP",
			"Weight":1
		},
		{
			"ParentName":"GSC - Finance",
			"ComponentName":"GRPFTR",
			"Weight":1
		},
		{
			"ParentName":"GSC - Finance",
			"ComponentName":"GRPFBS",
			"Weight":1
		},
		{
			"ParentName":"IT",
			"ComponentName":"Group IT Finance",
			"Weight":1
		},
		{
			"ParentName":"Group IT Finance",
			"ComponentName":"Group - Finance TFM",
			"Weight":1
		},
		{
			"ParentName":"Group IT Finance",
			"ComponentName":"Group - Finance IT DEV",
			"Weight":1
		},
		{
			"ParentName":"Group IT Finance",
			"ComponentName":"Group - Finance IT",
			"Weight":1
		},
		{
			"ParentName":"Group - Finance IT",
			"ComponentName":"GRPFIT",
			"Weight":1
		},
		{
			"ParentName":"Group - Finance IT DEV",
			"ComponentName":"GRPFDV",
			"Weight":1
		},
		{
			"ParentName":"Group - Finance TFM",
			"ComponentName":"GRPFTM",
			"Weight":1
		},
		{
			"ParentName":"Projects",
			"ComponentName":"Local - Other",
			"Weight":1
		},
		{
			"ParentName":"Projects",
			"ComponentName":"Group - Projects",
			"Weight":1
		},
		{
			"ParentName":"Group - Projects",
			"ComponentName":"GRPPRJ",
			"Weight":1
		}
	],
	"Subsets@Code.links":
	[
		"MA_Dept.subsets/All depts.json",
		"MA_Dept.subsets/All Leaves.json",
		"MA_Dept.subsets/ZZZ.json"
	]
}