{
	"@type":"Hierarchy",
	"Name":"Cashflow Consol Layer",
	"Elements":
	[
		{
			"Name":"Phasing",
			"Type":"Numeric"
		},
		{
			"Name":"Source",
			"Type":"Numeric"
		},
		{
			"Name":"Consolidated Cashflow",
			"Type":"Consolidated"
		},
		{
			"Name":"Consolidated Manual Adjustments",
			"Type":"Numeric"
		},
		{
			"Name":"Cashflow",
			"Type":"Consolidated"
		},
		{
			"Name":"Consolidated Eliminations",
			"Type":"Numeric"
		},
		{
			"Name":"Manual Adjustments",
			"Type":"Numeric"
		},
		{
			"Name":"Elimination",
			"Type":"Numeric"
		}
	],
	"Edges":
	[
		{
			"ParentName":"Consolidated Cashflow",
			"ComponentName":"Cashflow",
			"Weight":1
		},
		{
			"ParentName":"Consolidated Cashflow",
			"ComponentName":"Consolidated Eliminations",
			"Weight":1
		},
		{
			"ParentName":"Consolidated Cashflow",
			"ComponentName":"Consolidated Manual Adjustments",
			"Weight":1
		},
		{
			"ParentName":"Cashflow",
			"ComponentName":"Source",
			"Weight":1
		},
		{
			"ParentName":"Cashflow",
			"ComponentName":"Phasing",
			"Weight":1
		},
		{
			"ParentName":"Cashflow",
			"ComponentName":"Elimination",
			"Weight":1
		},
		{
			"ParentName":"Cashflow",
			"ComponentName":"Manual Adjustments",
			"Weight":1
		}
	],
	"Subsets@Code.links":
	[
		"Cashflow Consol Layer.subsets/Default.json"
	]
}