{
	"@type":"Subset",
	"Name":"Report Format",
	"Elements":
	[
		{
			"@id":"Dimensions('TM1 Accounts')/Hierarchies('TM1 Accounts')/Elements('L1_Transaction Count')"
		},
		{
			"@id":"Dimensions('TM1 Accounts')/Hierarchies('TM1 Accounts')/Elements('L1_TTV')"
		},
		{
			"@id":"Dimensions('TM1 Accounts')/Hierarchies('TM1 Accounts')/Elements('Net Sales')"
		},
		{
			"@id":"Dimensions('TM1 Accounts')/Hierarchies('TM1 Accounts')/Elements('Commission Received Point of Sale')"
		},
		{
			"@id":"Dimensions('TM1 Accounts')/Hierarchies('TM1 Accounts')/Elements('L2_MSM/VCF')"
		},
		{
			"@id":"Dimensions('TM1 Accounts')/Hierarchies('TM1 Accounts')/Elements('Professional Fees')"
		},
		{
			"@id":"Dimensions('TM1 Accounts')/Hierarchies('TM1 Accounts')/Elements('Sales Merchant Fees')"
		},
		{
			"@id":"Dimensions('TM1 Accounts')/Hierarchies('TM1 Accounts')/Elements('L1_Wings24')"
		},
		{
			"@id":"Dimensions('TM1 Accounts')/Hierarchies('TM1 Accounts')/Elements('Intercompany Charge Out')"
		},
		{
			"@id":"Dimensions('TM1 Accounts')/Hierarchies('TM1 Accounts')/Elements('Total Revenue')"
		},
		{
			"@id":"Dimensions('TM1 Accounts')/Hierarchies('TM1 Accounts')/Elements('Net Sales')"
		},
		{
			"@id":"Dimensions('TM1 Accounts')/Hierarchies('TM1 Accounts')/Elements('Commission Received Point of Sale')"
		},
		{
			"@id":"Dimensions('TM1 Accounts')/Hierarchies('TM1 Accounts')/Elements('L2_MSM/VCF')"
		},
		{
			"@id":"Dimensions('TM1 Accounts')/Hierarchies('TM1 Accounts')/Elements('Professional Fees')"
		},
		{
			"@id":"Dimensions('TM1 Accounts')/Hierarchies('TM1 Accounts')/Elements('L1_Wings24')"
		},
		{
			"@id":"Dimensions('TM1 Accounts')/Hierarchies('TM1 Accounts')/Elements('L2_Direct Costs')"
		},
		{
			"@id":"Dimensions('TM1 Accounts')/Hierarchies('TM1 Accounts')/Elements('Total Gross Profit POS')"
		},
		{
			"@id":"Dimensions('TM1 Accounts')/Hierarchies('TM1 Accounts')/Elements('Total Revenue')"
		},
		{
			"@id":"Dimensions('TM1 Accounts')/Hierarchies('TM1 Accounts')/Elements('Net Sales')"
		},
		{
			"@id":"Dimensions('TM1 Accounts')/Hierarchies('TM1 Accounts')/Elements('Commission Received Point of Sale')"
		},
		{
			"@id":"Dimensions('TM1 Accounts')/Hierarchies('TM1 Accounts')/Elements('L2_MSM/VCF')"
		},
		{
			"@id":"Dimensions('TM1 Accounts')/Hierarchies('TM1 Accounts')/Elements('Professional Fees')"
		},
		{
			"@id":"Dimensions('TM1 Accounts')/Hierarchies('TM1 Accounts')/Elements('L1_Wings24')"
		},
		{
			"@id":"Dimensions('TM1 Accounts')/Hierarchies('TM1 Accounts')/Elements('L2_Direct Costs')"
		},
		{
			"@id":"Dimensions('TM1 Accounts')/Hierarchies('TM1 Accounts')/Elements('L1_GDS Revenue')"
		},
		{
			"@id":"Dimensions('TM1 Accounts')/Hierarchies('TM1 Accounts')/Elements('L1_Overrides')"
		},
		{
			"@id":"Dimensions('TM1 Accounts')/Hierarchies('TM1 Accounts')/Elements('L1_Commission Received - Non- point of sale')"
		},
		{
			"@id":"Dimensions('TM1 Accounts')/Hierarchies('TM1 Accounts')/Elements('L1_Other income/Incidental income')"
		},
		{
			"@id":"Dimensions('TM1 Accounts')/Hierarchies('TM1 Accounts')/Elements('L1_F/X Margin')"
		},
		{
			"@id":"Dimensions('TM1 Accounts')/Hierarchies('TM1 Accounts')/Elements('L1_ADM')"
		},
		{
			"@id":"Dimensions('TM1 Accounts')/Hierarchies('TM1 Accounts')/Elements('Process Errors')"
		},
		{
			"@id":"Dimensions('TM1 Accounts')/Hierarchies('TM1 Accounts')/Elements('L1_Merchant Fees')"
		},
		{
			"@id":"Dimensions('TM1 Accounts')/Hierarchies('TM1 Accounts')/Elements('L1_GDS Costs')"
		},
		{
			"@id":"Dimensions('TM1 Accounts')/Hierarchies('TM1 Accounts')/Elements('L1_Share Cost Recovery')"
		},
		{
			"@id":"Dimensions('TM1 Accounts')/Hierarchies('TM1 Accounts')/Elements('Gross Profit')"
		},
		{
			"@id":"Dimensions('TM1 Accounts')/Hierarchies('TM1 Accounts')/Elements('Total GP %')"
		},
		{
			"@id":"Dimensions('TM1 Accounts')/Hierarchies('TM1 Accounts')/Elements('L1_Salaries & Benefits')"
		},
		{
			"@id":"Dimensions('TM1 Accounts')/Hierarchies('TM1 Accounts')/Elements('GSC Allocation')"
		},
		{
			"@id":"Dimensions('TM1 Accounts')/Hierarchies('TM1 Accounts')/Elements('Non GSC Allocation')"
		},
		{
			"@id":"Dimensions('TM1 Accounts')/Hierarchies('TM1 Accounts')/Elements('Contract & Temporary Labour')"
		},
		{
			"@id":"Dimensions('TM1 Accounts')/Hierarchies('TM1 Accounts')/Elements('T&E')"
		},
		{
			"@id":"Dimensions('TM1 Accounts')/Hierarchies('TM1 Accounts')/Elements('Staff welfare & Training')"
		},
		{
			"@id":"Dimensions('TM1 Accounts')/Hierarchies('TM1 Accounts')/Elements('Incentives & Commission')"
		},
		{
			"@id":"Dimensions('TM1 Accounts')/Hierarchies('TM1 Accounts')/Elements('L1_Recruitment Fees')"
		},
		{
			"@id":"Dimensions('TM1 Accounts')/Hierarchies('TM1 Accounts')/Elements('Staff Costs')"
		},
		{
			"@id":"Dimensions('TM1 Accounts')/Hierarchies('TM1 Accounts')/Elements('Facilities Expense')"
		},
		{
			"@id":"Dimensions('TM1 Accounts')/Hierarchies('TM1 Accounts')/Elements('Data & Telecoms')"
		},
		{
			"@id":"Dimensions('TM1 Accounts')/Hierarchies('TM1 Accounts')/Elements('Office Equipment')"
		},
		{
			"@id":"Dimensions('TM1 Accounts')/Hierarchies('TM1 Accounts')/Elements('L1_Insurance')"
		},
		{
			"@id":"Dimensions('TM1 Accounts')/Hierarchies('TM1 Accounts')/Elements('Printing & Stationary')"
		},
		{
			"@id":"Dimensions('TM1 Accounts')/Hierarchies('TM1 Accounts')/Elements('L1_IT Development')"
		},
		{
			"@id":"Dimensions('TM1 Accounts')/Hierarchies('TM1 Accounts')/Elements('L1_Software Licences')"
		},
		{
			"@id":"Dimensions('TM1 Accounts')/Hierarchies('TM1 Accounts')/Elements('Infrastructure')"
		},
		{
			"@id":"Dimensions('TM1 Accounts')/Hierarchies('TM1 Accounts')/Elements('Audit & Accountancy Fees')"
		},
		{
			"@id":"Dimensions('TM1 Accounts')/Hierarchies('TM1 Accounts')/Elements('L1_Subscriptions')"
		},
		{
			"@id":"Dimensions('TM1 Accounts')/Hierarchies('TM1 Accounts')/Elements('L1_Bank Charges')"
		},
		{
			"@id":"Dimensions('TM1 Accounts')/Hierarchies('TM1 Accounts')/Elements('L1_Legal Fees')"
		},
		{
			"@id":"Dimensions('TM1 Accounts')/Hierarchies('TM1 Accounts')/Elements('L1_Consultation Fees')"
		},
		{
			"@id":"Dimensions('TM1 Accounts')/Hierarchies('TM1 Accounts')/Elements('L1_Directors Fees')"
		},
		{
			"@id":"Dimensions('TM1 Accounts')/Hierarchies('TM1 Accounts')/Elements('L1_Bad Debts')"
		},
		{
			"@id":"Dimensions('TM1 Accounts')/Hierarchies('TM1 Accounts')/Elements('L1_Withholding Tax')"
		},
		{
			"@id":"Dimensions('TM1 Accounts')/Hierarchies('TM1 Accounts')/Elements('Other Overheads')"
		},
		{
			"@id":"Dimensions('TM1 Accounts')/Hierarchies('TM1 Accounts')/Elements('Other Cost')"
		},
		{
			"@id":"Dimensions('TM1 Accounts')/Hierarchies('TM1 Accounts')/Elements('Intra Regional Allocation')"
		},
		{
			"@id":"Dimensions('TM1 Accounts')/Hierarchies('TM1 Accounts')/Elements('Total Cost before Shared Service')"
		},
		{
			"@id":"Dimensions('TM1 Accounts')/Hierarchies('TM1 Accounts')/Elements('Local EBITDA')"
		},
		{
			"@id":"Dimensions('TM1 Accounts')/Hierarchies('TM1 Accounts')/Elements('Group Overheads Shared Costs')"
		},
		{
			"@id":"Dimensions('TM1 Accounts')/Hierarchies('TM1 Accounts')/Elements('L1_Global Technology')"
		},
		{
			"@id":"Dimensions('TM1 Accounts')/Hierarchies('TM1 Accounts')/Elements('L1_Group Administration')"
		},
		{
			"@id":"Dimensions('TM1 Accounts')/Hierarchies('TM1 Accounts')/Elements('Total Costs')"
		},
		{
			"@id":"Dimensions('TM1 Accounts')/Hierarchies('TM1 Accounts')/Elements('Sustainable EBITDA')"
		},
		{
			"@id":"Dimensions('TM1 Accounts')/Hierarchies('TM1 Accounts')/Elements('Exceptional Items & Restructure')"
		},
		{
			"@id":"Dimensions('TM1 Accounts')/Hierarchies('TM1 Accounts')/Elements('L1_Minority')"
		},
		{
			"@id":"Dimensions('TM1 Accounts')/Hierarchies('TM1 Accounts')/Elements('Management Allocation Reversal')"
		},
		{
			"@id":"Dimensions('TM1 Accounts')/Hierarchies('TM1 Accounts')/Elements('L1_Profit & (Loss) on Foreign Exchange')"
		},
		{
			"@id":"Dimensions('TM1 Accounts')/Hierarchies('TM1 Accounts')/Elements('Reported EBITDA')"
		},
		{
			"@id":"Dimensions('TM1 Accounts')/Hierarchies('TM1 Accounts')/Elements('Depreciation & Amortisation')"
		},
		{
			"@id":"Dimensions('TM1 Accounts')/Hierarchies('TM1 Accounts')/Elements('Right of use IFR15')"
		},
		{
			"@id":"Dimensions('TM1 Accounts')/Hierarchies('TM1 Accounts')/Elements('Net Interest Paid')"
		},
		{
			"@id":"Dimensions('TM1 Accounts')/Hierarchies('TM1 Accounts')/Elements('Income Tax')"
		},
		{
			"@id":"Dimensions('TM1 Accounts')/Hierarchies('TM1 Accounts')/Elements('Earnings')"
		},
		{
			"@id":"Dimensions('TM1 Accounts')/Hierarchies('TM1 Accounts')/Elements('Statistics')"
		},
		{
			"@id":"Dimensions('TM1 Accounts')/Hierarchies('TM1 Accounts')/Elements('L1_FTE count Local')"
		},
		{
			"@id":"Dimensions('TM1 Accounts')/Hierarchies('TM1 Accounts')/Elements('L1_FTE count Allocated')"
		},
		{
			"@id":"Dimensions('TM1 Accounts')/Hierarchies('TM1 Accounts')/Elements('FTE Total')"
		}
	]
}